textforgepy/__init__.py
textforgepy/main.py
textforgepy/prompts.py
textforgepy-2025.12.21090031.dist-info/METADATA
textforgepy-2025.12.21090031.dist-info/WHEEL
textforgepy-2025.12.21090031.dist-info/top_level.txt
textforgepy-2025.12.21090031.dist-info/RECORD
