Metadata-Version: 2.4
Name: textforgepy
Version: 2025.12.21090031
Summary: A new package designed to transform unstructured text inputs into standardized, machine-readable outputs. This tool focuses on domains where consistency and format are critical, such as technical docu
Author-email: textforgepy <hi@eugene.plus>
License: MIT
Project-URL: Homepage, https://github.com/chigwell/textforgepy
Requires-Python: >=3.9
Requires-Dist: langchain-llm7>=0.0.0
Requires-Dist: llmatch-messages>=0.0.0
Requires-Dist: langchain-core>=0.3.0
